ConfClr/CP.py
ConfClr/ConfClr.py
ConfClr/ConfCred.py
ConfClr/Distance.py
ConfClr/NearestNeighbour.py
ConfClr/NonConformityMeasure.py
ConfClr/Score.py
ConfClr/__init__.py
ConfClr/version.py
ConfClr-0.1.4.dist-info/METADATA
ConfClr-0.1.4.dist-info/WHEEL
ConfClr-0.1.4.dist-info/top_level.txt
ConfClr-0.1.4.dist-info/RECORD
