Metadata-Version: 2.1
Name: ConfClr
Version: 0.1.4
Summary: Conformal Prediction Framework for Binary Classification
Home-page: UNKNOWN
Author: Rahul Vishwakarma
Author-email: vishwr7@gmail.com
License: UNKNOWN
Platform: UNKNOWN
